wagtail_webradio/__init__.py
wagtail_webradio/apps.py
wagtail_webradio/blocks.py
wagtail_webradio/forms.py
wagtail_webradio/models.py
wagtail_webradio/panels.py
wagtail_webradio/utils.py
wagtail_webradio/validators.py
wagtail_webradio/wagtail_hooks.py
wagtail_webradio/widgets.py
wagtail_webradio/components/__init__.py
wagtail_webradio/components/player.py
wagtail_webradio/locale/fr/LC_MESSAGES/django.mo
wagtail_webradio/locale/fr/LC_MESSAGES/django.po
wagtail_webradio/management/__init__.py
wagtail_webradio/management/commands/__init__.py
wagtail_webradio/management/commands/migrateradioshows.py
wagtail_webradio/migrations/0001_initial.py
wagtail_webradio/migrations/0002_podcast_duration.py
wagtail_webradio/migrations/0003_sound_file.py
wagtail_webradio/migrations/0004_alter_podcast_sound_file.py
wagtail_webradio/migrations/0005_podcastpage_radioshowpage_taggedpodcastpage_and_more.py
wagtail_webradio/migrations/__init__.py
wagtail_webradio/static/wagtail_webradio/admin/css/clearable_file_input.css
wagtail_webradio/static/wagtail_webradio/admin/js/podcast-form.js
wagtail_webradio/static/wagtail_webradio/player/js/main.js
wagtail_webradio/static/wagtail_webradio/player/js/main.js.map
wagtail_webradio/templates/wagtail_webradio/admin/tables/navigate_to_podcasts_cell.html
wagtail_webradio/templates/wagtail_webradio/admin/widgets/clearable_file_input.html
wagtail_webradio/templates/wagtail_webradio/components/player.html
wagtail_webradio/templates/wagtail_webradio/icons/broadcast.svg
wagtail_webradio/templates/wagtail_webradio/icons/headphone.svg
wagtail_webradio/templates/wagtail_webradio/icons/microphone.svg
wagtail_webradio/views/__init__.py
wagtail_webradio/views/admin.py
wagtail_webradio-0.7.0.dist-info/METADATA
wagtail_webradio-0.7.0.dist-info/WHEEL
wagtail_webradio-0.7.0.dist-info/licenses/LICENSE
wagtail_webradio-0.7.0.dist-info/RECORD
