Metadata-Version: 2.4
Name: wagtail_webradio
Version: 0.7.0
Summary: Manage your web radio - e.g. podcasts, programs - in Wagtail
Project-URL: Repository, https://framagit.org/cliss21/wagtail-webradio
Project-URL: Issues, https://framagit.org/cliss21/wagtail-webradio/-/issues
Author-email: Cliss XXI <contact@cliss21.com>
License-Expression: AGPL-3.0-or-later
License-File: LICENSE
Keywords: radio,wagtail
Classifier: Development Status :: 3 - Alpha
Classifier: Environment :: Web Environment
Classifier: Framework :: Django
Classifier: Framework :: Wagtail
Classifier: Intended Audience :: Developers
Classifier: License :: OSI Approved :: GNU Affero General Public License v3
Classifier: Programming Language :: Python :: 3
Classifier: Programming Language :: Python :: 3.10
Classifier: Programming Language :: Python :: 3.11
Classifier: Programming Language :: Python :: 3.12
Classifier: Programming Language :: Python :: 3.13
Requires-Python: >=3.10
Requires-Dist: django>=4.2
Requires-Dist: filetype~=1.2.0
Requires-Dist: wagtail>=7.0
Provides-Extra: components
Requires-Dist: django-unicorn==0.43.1; extra == 'components'
